axioforce_sdk/__init__.py
axioforce_sdk/axioforce_c_api.dll
axioforce_sdk/cli.py
axioforce_sdk/libaxioforce_c_api.dylib
axioforce_sdk/sdk.py
axioforce_sdk-1.0.1.dist-info/METADATA
axioforce_sdk-1.0.1.dist-info/WHEEL
axioforce_sdk-1.0.1.dist-info/entry_points.txt
axioforce_sdk-1.0.1.dist-info/top_level.txt
axioforce_sdk-1.0.1.dist-info/RECORD
