Metadata-Version: 2.4
Name: axioforce-sdk
Version: 1.0.1
Summary: Python SDK for Axioforce sensor devices
Home-page: https://github.com/axioforce/axioforce-python-sdk
Author: Axioforce Team
Author-email: Axioforce Team <support@axioforce.com>
Maintainer-email: Axioforce Team <support@axioforce.com>
License: MIT
Project-URL: Homepage, https://github.com/axioforce/axioforce-python-sdk
Project-URL: Documentation, https://github.com/axioforce/axioforce-python-sdk/blob/main/README_SDK.md
Project-URL: Repository, https://github.com/axioforce/axioforce-python-sdk
Project-URL: Bug Tracker, https://github.com/axioforce/axioforce-python-sdk/issues
Keywords: sensor,force,measurement,axioforce,hardware,interface
Classifier: Development Status :: 4 - Beta
Classifier: Intended Audience :: Developers
Classifier: Intended Audience :: Science/Research
Classifier: License :: OSI Approved :: MIT License
Classifier: Operating System :: OS Independent
Classifier: Programming Language :: Python :: 3
Classifier: Programming Language :: Python :: 3.7
Classifier: Programming Language :: Python :: 3.8
Classifier: Programming Language :: Python :: 3.9
Classifier: Programming Language :: Python :: 3.10
Classifier: Programming Language :: Python :: 3.11
Classifier: Topic :: Scientific/Engineering
Classifier: Topic :: Software Development :: Libraries :: Python Modules
Requires-Python: >=3.7
Requires-Dist: typing-extensions>=3.7.4
Dynamic: author
Dynamic: home-page
Dynamic: requires-python
